xenavalkyrie/__init__.py
xenavalkyrie/xena_app.py
xenavalkyrie/xena_filter.py
xenavalkyrie/xena_object.py
xenavalkyrie/xena_port.py
xenavalkyrie/xena_statistics_view.py
xenavalkyrie/xena_stream.py
xenavalkyrie/xena_tshark.py
xenavalkyrie/api/BaseSocket.py
xenavalkyrie/api/__init__.py
xenavalkyrie/api/xena_cli.py
xenavalkyrie/api/xena_keepalive.py
xenavalkyrie/api/xena_rest.py
xenavalkyrie/api/xena_socket.py
xenavalkyrie/samples/__init__.py
xenavalkyrie/samples/connect_and_read_stats.py
xenavalkyrie/samples/dhcp_server.xpc
xenavalkyrie/samples/dhcp_server_full.py
xenavalkyrie/samples/test_config_1.xpc
xenavalkyrie/samples/test_config_long_packets.xpc
xenavalkyrie/samples/xena_line_test.py
xenavalkyrie/samples/xena_run_streams_with_capture.py
xenavalkyrie/samples/xena_sample_from_pcap.py
xenavalkyrie/samples/xena_samples.py
xenavalkyrie-3.0.1.dist-info/License.txt
xenavalkyrie-3.0.1.dist-info/METADATA
xenavalkyrie-3.0.1.dist-info/WHEEL
xenavalkyrie-3.0.1.dist-info/top_level.txt
xenavalkyrie-3.0.1.dist-info/RECORD
