Metadata-Version: 2.1
Name: xenavalkyrie
Version: 3.0.1
Summary: Python OO API package to manage Xena Valkyrie traffic generator
Home-page: https://github.com/shmir/PyXenaValkyrie/
Author: Yoram Shamir
Author-email: yoram@ignissoft.com
License: Apache Software License
Keywords: xena valkyrie l2l3 test tool automation api
Platform: any
Classifier: Development Status :: 5 - Production/Stable
Classifier: Natural Language :: English
Classifier: License :: OSI Approved :: Apache Software License
Classifier: Intended Audience :: Developers
Classifier: Operating System :: OS Independent
Classifier: Topic :: Software Development :: Testing
Classifier: Programming Language :: Python :: 3.7
Classifier: Programming Language :: Python :: 3.8
Classifier: Programming Language :: Python :: 3.9
Requires-Dist: future
Requires-Dist: requests
Requires-Dist: pypacker (==4.9)
Requires-Dist: pytrafficgen (<3.1.0,>=3.0.5)
